insteonplm/__init__.py
insteonplm/address.py
insteonplm/constants.py
insteonplm/linkedDevices.py
insteonplm/messagecallback.py
insteonplm/plm.py
insteonplm/tools.py
insteonplm/utils.py
insteonplm/devices/__init__.py
insteonplm/devices/climateControl.py
insteonplm/devices/dimmableLightingControl.py
insteonplm/devices/generalController.py
insteonplm/devices/ipdb.py
insteonplm/devices/securityHealthSafety.py
insteonplm/devices/sensorsActuators.py
insteonplm/devices/switchedLightingControl.py
insteonplm/devices/unknowndevice.py
insteonplm/devices/windowCoverings.py
insteonplm/devices/x10.py
insteonplm/messages/__init__.py
insteonplm/messages/allLinkCleanupFailureReport.py
insteonplm/messages/allLinkCleanupStatusReport.py
insteonplm/messages/allLinkComplete.py
insteonplm/messages/allLinkRecordResponse.py
insteonplm/messages/buttonEventReport.py
insteonplm/messages/cancelAllLinking.py
insteonplm/messages/extendedReceive.py
insteonplm/messages/extendedSend.py
insteonplm/messages/getFirstAllLinkRecord.py
insteonplm/messages/getIMInfo.py
insteonplm/messages/getImConfiguration.py
insteonplm/messages/getNextAllLinkRecord.py
insteonplm/messages/manageAllLinkRecord.py
insteonplm/messages/message.py
insteonplm/messages/messageFlags.py
insteonplm/messages/resetIM.py
insteonplm/messages/sendAlllinkCommand.py
insteonplm/messages/setImConfiguration.py
insteonplm/messages/standardReceive.py
insteonplm/messages/standardSend.py
insteonplm/messages/startAllLinking.py
insteonplm/messages/userReset.py
insteonplm/messages/userdata.py
insteonplm/messages/x10received.py
insteonplm/messages/x10send.py
insteonplm/states/__init__.py
insteonplm/states/cover.py
insteonplm/states/dimmable.py
insteonplm/states/onOff.py
insteonplm/states/sensor.py
insteonplm/states/statusReport.py
insteonplm/states/thermostat.py
insteonplm/states/x10.py
tests/__init__.py
tests/mockCallbacks.py
tests/mockConnection.py
tests/mockPLM.py
tests/test_address.py
tests/test_aldb.py
tests/test_device.py
insteonplm-0.15.4.dist-info/LICENSE
insteonplm-0.15.4.dist-info/METADATA
insteonplm-0.15.4.dist-info/WHEEL
insteonplm-0.15.4.dist-info/entry_points.txt
insteonplm-0.15.4.dist-info/top_level.txt
insteonplm-0.15.4.dist-info/zip-safe
insteonplm-0.15.4.dist-info/RECORD
