Metadata-Version: 2.1
Name: insteonplm
Version: 0.15.4
Summary: Python API for controlling Insteon PowerLinc Modems
Home-page: https://github.com/nugget/python-insteonplm
Author: David McNett
Author-email: nugget@macnugget.org
License: MIT License
Keywords: home,automation,insteon
Platform: any
Classifier: Development Status :: 4 - Beta
Classifier: Intended Audience :: Developers
Classifier: License :: OSI Approved :: MIT License
Classifier: Operating System :: OS Independent
Classifier: Programming Language :: Python :: 3.5
Classifier: Programming Language :: Python :: 3.6
Classifier: Programming Language :: Python :: 3.7
Classifier: Topic :: Home Automation
Classifier: Topic :: Software Development :: Libraries :: Python Modules
Requires-Dist: pyserial (==3.2.0)
Requires-Dist: pyserial-asyncio
Requires-Dist: async-timeout
Requires-Dist: aiohttp
